{
  "BaseFAQ": {
    "description": "Auto imported from components/base/FAQ.vue"
  },
  "BaseFooter": {
    "description": "Auto imported from components/base/Footer.vue"
  },
  "BaseHeader": {
    "description": "Auto imported from components/base/Header.vue"
  },
  "BaseLogo": {
    "description": "Auto imported from components/base/Logo.vue"
  },
  "SwiperCrowdsale": {
    "description": "Auto imported from components/swiper/Crowdsale.vue"
  },
  "SwiperSlideshow": {
    "description": "Auto imported from components/swiper/Slideshow.vue"
  },
  "SwiperTeam": {
    "description": "Auto imported from components/swiper/Team.vue"
  },
  "SectionAdvantages": {
    "description": "Auto imported from components/section/Advantages.vue"
  },
  "SectionBenefits": {
    "description": "Auto imported from components/section/Benefits.vue"
  },
  "SectionBlog": {
    "description": "Auto imported from components/section/Blog.vue"
  },
  "SectionCrowdsale": {
    "description": "Auto imported from components/section/Crowdsale.vue"
  },
  "SectionDetails": {
    "description": "Auto imported from components/section/Details.vue"
  },
  "SectionFeatures": {
    "description": "Auto imported from components/section/Features.vue"
  },
  "SectionPublicSale": {
    "description": "Auto imported from components/section/PublicSale.vue"
  },
  "SectionRoadmap": {
    "description": "Auto imported from components/section/Roadmap.vue"
  },
  "SectionServices": {
    "description": "Auto imported from components/section/Services.vue"
  },
  "SectionSpotlight": {
    "description": "Auto imported from components/section/Spotlight.vue"
  },
  "SectionSteps": {
    "description": "Auto imported from components/section/Steps.vue"
  },
  "SectionSupport": {
    "description": "Auto imported from components/section/Support.vue"
  }
}
